babymmlu/__init__.py
babymmlu/miniagi_parallel.py
babymmlu/utils.py
babymmlu-0.0.4.dist-info/METADATA
babymmlu-0.0.4.dist-info/WHEEL
babymmlu-0.0.4.dist-info/top_level.txt
babymmlu-0.0.4.dist-info/RECORD
