Metadata-Version: 2.1
Name: babymmlu
Version: 0.0.4
Summary: Sample implementation of babymmlu benchmark
Home-page: https://github.com/averkij/babymmlu
Author: Ivan Bychkov
Author-email: Sergei Averkiev <averoo@gmail.com>
Project-URL: Bug Tracker, https://github.com/averkij/babymmlu/issues
Classifier: Programming Language :: Python :: 3
Classifier: License :: OSI Approved :: GNU General Public License v3 (GPLv3)
Classifier: Operating System :: OS Independent
Requires-Python: >=3.6
Requires-Dist: transformers
Requires-Dist: datasets
Requires-Dist: torch
Requires-Dist: numpy
